{"adobe": ["ntuser"], "allowedenum": ["ntuser", "software"], "amcache": ["amcache"], "amcache_tln": ["amcache"], "appassoc": ["ntuser"], "appcertdlls": ["system"], "appcompatcache": ["system"], "appcompatcache_tln": ["system"], "appcompatflags": ["ntuser", "software"], "appinitdlls": ["software"], "appkeys": ["ntuser"], "appkeys_tln": ["ntuser"], "applets": ["ntuser"], "applets_tln": ["ntuser"], "apppaths": ["software", "ntuser"], "apppaths_tln": ["software"], "appspecific": ["ntuser"], "appx": ["ntuser", "usrclass"], "appx_tln": ["ntuser", "usrclass"], "arpcache": ["ntuser"], "at": ["software"], "at_tln": ["software"], "attachmgr": ["ntuser"], "attachmgr_tln": ["ntuser"], "audiodev": ["software"], "auditpol": ["security"], "backuprestore": ["system"], "bam": ["system"], "bam_tln": ["system"], "base": ["all"], "baseline": ["all"], "btconfig": ["software"], "bthenum": ["system"], "bthport": ["system"], "bthport_tln": ["system"], "cached": ["ntuser"], "cached_tln": ["ntuser"], "calibrator": ["software"], "ccleaner": ["ntuser"],"clsid": ["software"], "clsid_tln": ["software"], "cmd_shell": ["software"], "cmdproc": ["ntuser"], "cmdproc_tln": ["ntuser"], "codepage": ["system"], "comdlg32": ["ntuser"], "compdesc": ["ntuser"], "compname": ["system"], "cortana": ["ntuser"], "crashcontrol": ["system"], "cred": ["system"], "cred_tln": ["system"], "dafupnp": ["system"], "dcom": ["software"], "ddo": ["ntuser"], "defbrowser": ["software"], "defender": ["software"], "del": ["all"], "del_tln": ["all"], "devclass": ["system"], "diag_sr": ["system"], "direct": ["software"], "direct_tln": ["software"], "disablelastaccess": ["system"], "disablemru": ["ntuser", "software"], "disableremotescm": ["system"], "disablesr": ["software"], "drivers32": ["software"], "emdmgmt": ["software"], "environment": ["ntuser", "system"], "eventlog": ["system"], "eventlogs": ["system"], "execpolicy": ["software"], "featureusage": ["ntuser"], "fileless": ["all"], "findexes": ["all"], "fw_config": ["system"], "gpohist": ["software"], "gpohist_tln": ["software"], "heap": ["software"], "ica_sessions": ["software"], "identities": ["ntuser"], "ie_settings": ["ntuser"], "ie_version": ["software"], "imagedev": ["system"], "imagefile": ["software"], "injectdll64": ["ntuser", "software"], "inprocserver": ["software"], "installer": ["software"], "ips": ["system"], "jumplistdata": ["ntuser"], "killsuit": ["software"], "killsuit_tln": ["software"], "knowndev": ["ntuser"], "landesk": ["software"], "landesk_tln": ["software"], "lastloggedon": ["software"], "licenses": ["software"], "listsoft": ["ntuser"], "load": ["ntuser"], "logonstats": ["ntuser"], "lsa": ["system"], "lxss": ["ntuser"], "lxss_tln": ["ntuser"], "macaddr": ["system", "software"], "mixer": ["ntuser"], "mixer_tln": ["ntuser"], "mmc": ["ntuser"], "mmc_tln": ["ntuser"], "mmo": ["ntuser"], "mndmru": ["ntuser"], "mndmru_tln": ["ntuser"], "mountdev": ["system"], "mountdev2": ["system"], "mp2": ["ntuser"], "mp2_tln": ["ntuser"], "mpmru": ["ntuser"], "msis": ["software"], "msoffice": ["ntuser"], "msoffice_tln": ["ntuser"], "muicache": ["ntuser", "usrclass"], "muicache_tln": ["ntuser", "usrclass"], "nation": ["ntuser"], "netlogon": ["system"], "netsh": ["software"], "networkcards": ["software"], "networklist": ["software"], "networklist_tln": ["software"], "networksetup2": ["system"], "nic2": ["system"], "ntds": ["system"], "null": ["all"], "oisc": ["ntuser"], "onedrive": ["ntuser"], "onedrive_tln": ["ntuser"], "osversion": ["ntuser"], "osversion_tln": ["ntuser"], "outlook_search": ["ntuser"], "pagefile": ["system"], "pending": ["system"], "pendinggpos": ["ntuser"], "photos": ["usrclass"], "polacdms": ["security"], "portdev": ["software"], "powershellcore": ["software"], "prefetch": ["system"], "printdemon": ["software"], "printmon": ["system"], "printmon_tln": ["system"], "processor_architecture": ["system"], "profilelist": ["software"], "profiler": ["ntuser", "system"], "proxysettings": ["ntuser"], "pslogging": ["ntuser", "software"], "psscript": ["software"], "putty": ["ntuser"], "rdphint": ["ntuser"], "rdpnla": ["software"], "rdpport": ["system"], "recentapps": ["ntuser"], "recentapps_tln": ["ntuser"], "recentdocs": ["ntuser"], "recentdocs_tln": ["ntuser"], "remoteaccess": ["system"], "rlo": ["all"], "routes": ["system"], "run": ["ntuser", "software"], "runmru": ["ntuser"], "runmru_tln": ["ntuser"], "runonceex": ["software"], "runvirtual": ["ntuser", "software"], "runvirtual_tln": ["ntuser", "software"], "ryuk_gpo": ["software"], "samparse": ["sam"], "samparse_tln": ["sam"], "schedagent": ["software"], "scriptleturl": ["ntuser", "usrclass"], "searchscopes": ["ntuser"], "secctr": ["software"], "secrets": ["security"], "secrets_tln": ["security"], "securityproviders": ["system"], "services": ["system"], "sevenzip": ["ntuser"], "sfc": ["software"], "shares": ["system"], "shc": ["ntuser"], "shellbags": ["usrclass"], "shellbags_tln": ["usrclass"], "shellfolders": ["ntuser"], "shelloverlay": ["software"], "shimcache": ["system"], "shimcache_tln": ["system"], "shutdown": ["system"], "silentprocessexit": ["software"], "silentprocessexit_tln": ["software"], "sizes": ["all"], "slack": ["all"], "slack_tln": ["all"], "source_os": ["system"], "speech": ["ntuser"], "speech_tln": ["ntuser"], "spp_clients": ["software"], "srum": ["software"], "ssid": ["software"], "susclient": ["software"], "svc": ["system"], "svc_tln": ["system"], "svcdll": ["system"], "syscache": ["syscache"], "syscache_csv": ["syscache"], "syscache_tln": ["syscache"], "sysinternals": ["ntuser"], "sysinternals_tln": ["ntuser"], "systemindex": ["software"], "taskcache":["software"], "taskcache_tln":["software"], "tasks":["software"], "teamviewer":["software"], "termcert": ["system"], "termserv": ["system"], "thispcpolicy": ["software"], "timezone": ["system"], "tracing": ["software"], "tracing_tln": ["software"], "tsclient": ["ntuser"], "tsclient_tln": ["ntuser"], "typedpaths": ["ntuser"], "typedpaths_tln": ["ntuser"], "typedurls": ["ntuser"], "typedurls_tln": ["ntuser"], "typedurlstime": ["ntuser"], "typedurlstime_tln": ["ntuser"], "uac": ["software"], "uacbypass": ["usrclass", "software"], "uninstall": ["software", "ntuser"], "uninstall_tln": ["software", "ntuser"], "usb": ["system"], "usbdevices": ["system"], "usbstor": ["system"], "userassist": ["ntuser"], "userassist_tln": ["ntuser"], "vmware_vsphere_client": ["ntuser"], "volinfocache": ["software"], "wab": ["software"], "wab_tln": ["software"], "watp": ["software"], "wbem": ["software"], "wc_shares": ["ntuser"], "winevt": ["software"], "winlogon_tln": ["software"], "winrar": ["ntuser"], "winrar_tln": ["ntuser"], "winscp": ["ntuser"], "winscp_sessions": ["ntuser"], "winver": ["software"], "winver2": ["software"], "winzip": ["ntuser"], "wordwheelquery": ["ntuser"], "wordwheelquery_tln": ["ntuser"], "wow64": ["software"], "wpdbusenum": ["system"], "wsh_settings": ["software"]}
